llmstxt_architect/__init__.py
llmstxt_architect/cli.py
llmstxt_architect/extractor.py
llmstxt_architect/loader.py
llmstxt_architect/main.py
llmstxt_architect/styling.py
llmstxt_architect/summarizer.py
llmstxt_architect-0.6.1.dist-info/METADATA
llmstxt_architect-0.6.1.dist-info/WHEEL
llmstxt_architect-0.6.1.dist-info/entry_points.txt
llmstxt_architect-0.6.1.dist-info/licenses/LICENSE
llmstxt_architect-0.6.1.dist-info/RECORD
