Metadata-Version: 2.4
Name: llmstxt_architect
Version: 0.6.1
Summary: Design and build LLMs.txt knowledge structures by extracting and summarizing web content
Project-URL: Homepage, https://github.com/rlancemartin/llmstxt_architect
Author: lance@langchain.dev
License: MIT License
License-File: LICENSE
Requires-Python: >=3.10
Requires-Dist: beautifulsoup4>=4.13.3
Requires-Dist: httpx>=0.28.1
Requires-Dist: langchain-anthropic>=0.3.10
Requires-Dist: langchain-community>=0.3.20
Requires-Dist: langchain-ollama>=0.3.0
Requires-Dist: langchain>=0.3.21
Requires-Dist: lxml>=5.3.1
Requires-Dist: markdownify>=1.1.0
Provides-Extra: dev
Requires-Dist: black>=23.0.0; extra == 'dev'
Requires-Dist: isort>=5.12.0; extra == 'dev'
Requires-Dist: mypy>=1.0.0; extra == 'dev'
Requires-Dist: pytest>=7.0.0; extra == 'dev'
Requires-Dist: ruff>=0.0.275; extra == 'dev'
